azure/mgmt/servicelinker/__init__.py
azure/mgmt/servicelinker/_configuration.py
azure/mgmt/servicelinker/_patch.py
azure/mgmt/servicelinker/_service_linker_management_client.py
azure/mgmt/servicelinker/_vendor.py
azure/mgmt/servicelinker/_version.py
azure/mgmt/servicelinker/py.typed
azure/mgmt/servicelinker/aio/__init__.py
azure/mgmt/servicelinker/aio/_configuration.py
azure/mgmt/servicelinker/aio/_patch.py
azure/mgmt/servicelinker/aio/_service_linker_management_client.py
azure/mgmt/servicelinker/aio/operations/__init__.py
azure/mgmt/servicelinker/aio/operations/_linker_operations.py
azure/mgmt/servicelinker/aio/operations/_operations.py
azure/mgmt/servicelinker/models/__init__.py
azure/mgmt/servicelinker/models/_models_py3.py
azure/mgmt/servicelinker/models/_service_linker_management_client_enums.py
azure/mgmt/servicelinker/operations/__init__.py
azure/mgmt/servicelinker/operations/_linker_operations.py
azure/mgmt/servicelinker/operations/_operations.py
azure_mgmt_servicelinker-1.1.0.dist-info/LICENSE
azure_mgmt_servicelinker-1.1.0.dist-info/METADATA
azure_mgmt_servicelinker-1.1.0.dist-info/WHEEL
azure_mgmt_servicelinker-1.1.0.dist-info/top_level.txt
azure_mgmt_servicelinker-1.1.0.dist-info/RECORD
